{"noiseKey":{"private":{"type":"Buffer","data":"GGhoRDYl8oPcDH89PMa9SG1LB6gNsEmBnY1futkZAXc="},"public":{"type":"Buffer","data":"cdTbuRkTcEEuYa4K6UO6fs3HgfA3W2OIUOAFT/WMMgc="}},"pairingEphemeralKeyPair":{"private":{"type":"Buffer","data":"cFs0Z1bkf4iKHbI8EiyjftdZL/xblywXOArngTW+smc="},"public":{"type":"Buffer","data":"64x74R0raKm7RMx4nBhys9Z0mOBM8fAgXLIucFV1B24="}},"signedIdentityKey":{"private":{"type":"Buffer","data":"uAJ4elk4U8RGlrHaaGqH6yMYFNOO1WUYba9rWihgLE8="},"public":{"type":"Buffer","data":"cH6EZgM+4pLUm+Z1uSKP9j37LJxCAA7H5ee1ew/7Zws="}},"signedPreKey":{"keyPair":{"private":{"type":"Buffer","data":"4JPbFlqEjKxsRod/TcqKPnzEM9QUCHoqNh8hgnQzX2M="},"public":{"type":"Buffer","data":"t0CmUv3cyRfqY0gOmSiAF10cIEDdnq2M9JtbplfYLWQ="}},"signature":{"type":"Buffer","data":"gRhHIv0yt/o6Q0a3OlIXXc/0aeDrQl8tgtHNobX48Q60Sotx+kS06Q0lXFBolGIuAeRxXbqGhrHhPfNFu19jCw=="},"keyId":1},"registrationId":5,"advSecretKey":"z1uFeruwScOo7qST027axK9X9tXFxhixes0cRNPwGuY=","processedHistoryMessages":[{"key":{"remoteJid":"22677701726@s.whatsapp.net","fromMe":true,"id":"F3AA1F193D9C9881D44C8F6E86E8F571"},"messageTimestamp":1744470900},{"key":{"remoteJid":"22677701726@s.whatsapp.net","fromMe":true,"id":"B6B8A943E044A60011BC33A734514279"},"messageTimestamp":1744471338},{"key":{"remoteJid":"22677701726@s.whatsapp.net","fromMe":true,"id":"B06B6CF1C3244865095FF9CBFB0A9809"},"messageTimestamp":1744471429},{"key":{"remoteJid":"22677701726@s.whatsapp.net","fromMe":true,"id":"8C9F93CD56B9A7A461D52E5E6CD252DD"},"messageTimestamp":1744471513},{"key":{"remoteJid":"22677701726@s.whatsapp.net","fromMe":true,"id":"9A338DEB69FD900D4B47D6B6764BB085"},"messageTimestamp":1744471594},{"key":{"remoteJid":"22677701726@s.whatsapp.net","fromMe":true,"id":"9B3261C3D97DB08BDD8388772CFFE877"},"messageTimestamp":1744471664},{"key":{"remoteJid":"22677701726@s.whatsapp.net","fromMe":true,"id":"3C576256EA136269A7CF9EF083E12DB8"},"messageTimestamp":1744471737},{"key":{"remoteJid":"22677701726@s.whatsapp.net","fromMe":true,"id":"5DF0ECE5CEE83A68323D427ED42C2673"},"messageTimestamp":1744471810},{"key":{"remoteJid":"22677701726@s.whatsapp.net","fromMe":true,"id":"228DCBDCA901182EC54428300C162584"},"messageTimestamp":1744471879},{"key":{"remoteJid":"22677701726@s.whatsapp.net","fromMe":true,"id":"CBD654185D706E57D7A05026EEC992D2"},"messageTimestamp":1744471945},{"key":{"remoteJid":"22677701726@s.whatsapp.net","fromMe":true,"id":"6FBFEE2A83DD827B8B7EF49E2E3167A9"},"messageTimestamp":1744472018},{"key":{"remoteJid":"22677701726@s.whatsapp.net","fromMe":true,"id":"C622AEF8A304C7ECEF1B61C814D9F65E"},"messageTimestamp":1744472090},{"key":{"remoteJid":"22677701726@s.whatsapp.net","fromMe":true,"id":"6D6948B3AAEABC3FD0DE4E84072ED9EE"},"messageTimestamp":1744472163},{"key":{"remoteJid":"22677701726@s.whatsapp.net","fromMe":true,"id":"E0367F236CD897331E09CE2CAFFE3E35"},"messageTimestamp":1744472236},{"key":{"remoteJid":"22677701726@s.whatsapp.net","fromMe":true,"id":"358DC56F2B5532D52730048C8A505EFF"},"messageTimestamp":1744472304},{"key":{"remoteJid":"22677701726@s.whatsapp.net","fromMe":true,"id":"57B410721492B4659866FBE9B597E331"},"messageTimestamp":1744472390},{"key":{"remoteJid":"22677701726@s.whatsapp.net","fromMe":true,"id":"C52FF1BC1CD715D0977ECBA896B86F6C"},"messageTimestamp":1744472455},{"key":{"remoteJid":"22677701726@s.whatsapp.net","fromMe":true,"id":"2F7E4475070F21118E7CEE5B6021176F"},"messageTimestamp":1744472536},{"key":{"remoteJid":"22677701726@s.whatsapp.net","fromMe":true,"id":"70396159489A783BCFCC1E663A16F6F7"},"messageTimestamp":1744472603},{"key":{"remoteJid":"22677701726@s.whatsapp.net","fromMe":true,"id":"7211841C27D2614F1CCA7E3905717495"},"messageTimestamp":1744472663},{"key":{"remoteJid":"22677701726@s.whatsapp.net","fromMe":true,"id":"D93469AD5F8D7B747BECF3F093EC99C8"},"messageTimestamp":1744472732},{"key":{"remoteJid":"22677701726@s.whatsapp.net","fromMe":true,"id":"9EE0A066708B0CE92BAA66A6E38841FD"},"messageTimestamp":1744472809},{"key":{"remoteJid":"22677701726@s.whatsapp.net","fromMe":true,"id":"F0250674F4C310141553A18A882E4985"},"messageTimestamp":1744472880},{"key":{"remoteJid":"22677701726@s.whatsapp.net","fromMe":true,"id":"1C5092BA24B6C7523F0424CD0D36BAA3"},"messageTimestamp":1744472950},{"key":{"remoteJid":"22677701726@s.whatsapp.net","fromMe":true,"id":"6197F796852C29250414418DA1E52B7F"},"messageTimestamp":1744473014},{"key":{"remoteJid":"22677701726@s.whatsapp.net","fromMe":true,"id":"DF0C63E895C336698A1081426AF1D55C"},"messageTimestamp":1744473076},{"key":{"remoteJid":"22677701726@s.whatsapp.net","fromMe":true,"id":"9FB7064F06BBDF998D80E217BDC6FAFC"},"messageTimestamp":1744473137},{"key":{"remoteJid":"22677701726@s.whatsapp.net","fromMe":true,"id":"F9E7D5D6ABB9ABE54A0940313BA080BE"},"messageTimestamp":1744473217},{"key":{"remoteJid":"22677701726@s.whatsapp.net","fromMe":true,"id":"29AF20373A2EE2E92E300446502DF0A5"},"messageTimestamp":1744473292},{"key":{"remoteJid":"22677701726@s.whatsapp.net","fromMe":true,"id":"85D9F338C0BEC66CD1B62EF5A0EFEBBB"},"messageTimestamp":1744473362},{"key":{"remoteJid":"22677701726@s.whatsapp.net","fromMe":true,"id":"8B09B579C2FA32718319F482A41D0F51"},"messageTimestamp":1744473423},{"key":{"remoteJid":"22677701726@s.whatsapp.net","fromMe":true,"id":"4D17B2B11AEF869179E60BFD321113FE"},"messageTimestamp":1744473483}],"nextPreKeyId":338,"firstUnuploadedPreKeyId":338,"accountSyncCounter":1,"accountSettings":{"unarchiveChats":false},"deviceId":"wfjInPKrQoO1KZRJYSrmkA","phoneId":"4ec41f20-c33b-4d6b-ab06-4a2690362095","identityId":{"type":"Buffer","data":"NmyFlLRu7f+AKN3JmW8uph4/qtw="},"registered":false,"backupToken":{"type":"Buffer","data":"WHsivfjIplCCH1xsA1IvJzIxGIQ="},"registration":{},"account":{"details":"CJzx7d8CEPCF6r8GGAMgACgA","accountSignatureKey":"NnHyG0CVLZ9cohnoe2cme1jhF0PlITGwNLTCKPGM7Ug=","accountSignature":"2kHBFePkPcsCxQ5DANPHP6tNHdayXkAqRABLgaJSffqpfNr6569piRDpoYivgnqDZWNA9FT6MbaxRkh/oIQ3AA==","deviceSignature":"SbkpLJUXPYeQz587Lgw8hNBpWyA8X8OfZvPWVAFL5XkCtacMeJHxzG9wdmtuCKk0c9fFCH48hrBYPlsPCECBCA=="},"me":{"id":"22677701726:12@s.whatsapp.net","name":"Rodhackgang Dev","lid":"237425792131298:12@lid"},"signalIdentities":[{"identifier":{"name":"22677701726:12@s.whatsapp.net","deviceId":0},"identifierKey":{"type":"Buffer","data":"BTZx8htAlS2fXKIZ6HtnJntY4RdD5SExsDS0wijxjO1I"}}],"platform":"smba","routingInfo":{"type":"Buffer","data":"CAMIDQ=="},"lastAccountSyncTimestamp":1744798566,"myAppStateKeyId":"AAAAAHfP"}